compot/__init__.py
compot/composable.py
compot/datastructures.py
compot/widgets/__init__.py
compot/widgets/column.py
compot/widgets/main_window.py
compot/widgets/progressbar.py
compot/widgets/row.py
compot/widgets/statusbar.py
compot/widgets/text.py
tests/__init__.py
tests/ui/__init__.py
tests/ui/test_column.py
tests/ui/test_mainwindow.py
tests/ui/test_progressbar.py
tests/ui/test_row.py
tests/ui/test_statusbar.py
tests/ui/test_text.py
tests/unit/__init__.py
tests/unit/datastructures/__init__.py
tests/unit/datastructures/test_general_tree.py
compot_ui-0.2.3.dist-info/LICENSE.md
compot_ui-0.2.3.dist-info/METADATA
compot_ui-0.2.3.dist-info/WHEEL
compot_ui-0.2.3.dist-info/top_level.txt
compot_ui-0.2.3.dist-info/RECORD
