Metadata-Version: 2.1
Name: compot-ui
Version: 0.2.3
Summary: A small, stateless, fully compositional TUI framework.
Home-page: https://github.com/markovejnovic/compot
Author: Marko Vejnovic
Author-email: contact@markovejnovic.com
License: MIT
Platform: UNKNOWN
Classifier: Development Status :: 2 - Pre-Alpha
Classifier: Environment :: Console :: Curses
Classifier: Intended Audience :: Developers
Classifier: License :: OSI Approved :: MIT License
Classifier: Natural Language :: English
Classifier: Operating System :: Unix
Classifier: Programming Language :: Python :: 3.8
Classifier: Programming Language :: Python :: 3.9
Classifier: Programming Language :: Python :: 3.10
Classifier: Topic :: Software Development :: Libraries
License-File: LICENSE.md
Requires-Dist: wcwidth
